LICENSE.txt
MANIFEST.in
README.txt
k3lib.py
rotorlib.py
setup.py
steppirlib.py
config/k3.xml
config/rotor.xml
config/steppir.xml
rigcontrol.egg-info/PKG-INFO
rigcontrol.egg-info/SOURCES.txt
rigcontrol.egg-info/dependency_links.txt
rigcontrol.egg-info/requires.txt
rigcontrol.egg-info/top_level.txt
scripts/att
scripts/cwspeed
scripts/filter
scripts/fiq
scripts/k2
scripts/k3fixtime
scripts/k3time
scripts/k3ver
scripts/mode
scripts/nb
scripts/pa
scripts/power
scripts/qrg
scripts/qrg2
scripts/qsy
scripts/qsy2
scripts/rotor
scripts/sendcw
scripts/showtext
scripts/step
scripts/vfo