Metadata-Version: 1.0
Name: rigcontrol
Version: 0.3.15
Summary: Python rig control utilities and libraries for amateur radio equipment
Home-page: http://wa5znu.org/2009/02/python-rigcontrol
Author: Leigh L. Klotz, Jr. WA5ZNU
Author-email: leigh@wa5znu.org
License: Academic Free License (AFL)
Platform: POSIX
Classifier: Development Status :: 3 - Alpha
Classifier: Environment :: X11 Applications
Classifier: Intended Audience :: End Users/Desktop
Classifier: License :: OSI Approved :: Academic Free License (AFL)
Classifier: Natural Language :: English
Classifier: Operating System :: POSIX
Classifier: Programming Language :: Python
Classifier: Topic :: Communications :: Ham Radio
